tlstrust/__init__.py
tlstrust/context.py
tlstrust/util.py
tlstrust/cli/__init__.py
tlstrust/cli/__main__.py
tlstrust/stores/__init__.py
tlstrust/stores/android_10.py
tlstrust/stores/android_11.py
tlstrust/stores/android_12.py
tlstrust/stores/android_13.py
tlstrust/stores/android_14.py
tlstrust/stores/android_15.py
tlstrust/stores/android_2_2.py
tlstrust/stores/android_2_3.py
tlstrust/stores/android_3.py
tlstrust/stores/android_4.py
tlstrust/stores/android_4_4.py
tlstrust/stores/android_7.py
tlstrust/stores/android_8.py
tlstrust/stores/android_9.py
tlstrust/stores/android_latest.py
tlstrust/stores/ccadb.py
tlstrust/stores/certifi.py
tlstrust/stores/cloudflare.py
tlstrust/stores/cloudflare_ios.py
tlstrust/stores/cloudflare_nss.py
tlstrust/stores/cloudflare_osx.py
tlstrust/stores/cloudflare_ubuntu.py
tlstrust/stores/cloudflare_windows.py
tlstrust/stores/curl.py
tlstrust/stores/dart.py
tlstrust/stores/java.py
tlstrust/stores/mintsifry_rossii.py
tlstrust/stores/rustls.py
tlstrust-2.9.0.dist-info/LICENSE
tlstrust-2.9.0.dist-info/METADATA
tlstrust-2.9.0.dist-info/WHEEL
tlstrust-2.9.0.dist-info/entry_points.txt
tlstrust-2.9.0.dist-info/top_level.txt
tlstrust-2.9.0.dist-info/RECORD
