Metadata-Version: 2.1
Name: tlstrust
Version: 2.9.0
Summary: Utilities that assist with trust relationship checking of X.509 Certificates for various end-user devices with disparate root trust stores.
Author-email: Christopher Langton <chris@trivialsec.com>
License: GNU GENERAL PUBLIC LICENSE
Project-URL: Homepage, https://www.trivialsec.com
Project-URL: Source, https://gitlab.com/trivialsec/tlstrust
Project-URL: Bug Tracker, https://gitlab.com/trivialsec/tlstrust/-/issues
Classifier: Operating System :: OS Independent
Classifier: Programming Language :: Python :: 3
Classifier: License :: OSI Approved :: GNU General Public License v3 or later (GPLv3+)
Requires-Python: >=3.9
License-File: LICENSE
Requires-Dist: asn1crypto >=1.4.0
Requires-Dist: certifi >=2022.5.18.1
Requires-Dist: cryptography >=37.0.2
Requires-Dist: decorator
Requires-Dist: idna >=3.3
Requires-Dist: pycparser >=2.21
Requires-Dist: Pygments >=2.12.0
Requires-Dist: pyOpenSSL >=22.0.0
Requires-Dist: rich >=12.4.4
Requires-Dist: validators
Requires-Dist: retry
